README.txt
setup.cfg
setup.py
docs/HISTORY.txt
docs/LICENSE.GPL
docs/LICENSE.txt
docs/MANUAL.txt
raptus/__init__.py
raptus.article.reference.egg-info/PKG-INFO
raptus.article.reference.egg-info/SOURCES.txt
raptus.article.reference.egg-info/dependency_links.txt
raptus.article.reference.egg-info/entry_points.txt
raptus.article.reference.egg-info/namespace_packages.txt
raptus.article.reference.egg-info/not-zip-safe
raptus.article.reference.egg-info/requires.txt
raptus.article.reference.egg-info/top_level.txt
raptus/article/__init__.py
raptus/article/reference/__init__.py
raptus/article/reference/configure.zcml
raptus/article/reference/extender.py
raptus/article/reference/interfaces.py
raptus/article/reference/reference.py
raptus/article/reference/browser/__init__.py
raptus/article/reference/browser/configure.zcml
raptus/article/reference/browser/reference.pt
raptus/article/reference/browser/reference.py
raptus/article/reference/i18n/raptus.article-de.po
raptus/article/reference/i18n/raptus.article-fr.po
raptus/article/reference/i18n/raptus.article.pot