Metadata-Version: 1.0
Name: raptus.article.reference
Version: 2.0b6
Summary: Provides support for internal or external references on nested articles.
Home-page: http://raptus.com
Author: Raptus AG
Author-email: dev@raptus.com
License: GPL
Platform: UNKNOWN
Classifier: Programming Language :: Python
Classifier: Topic :: Software Development :: Libraries :: Python Modules
